ebusdpy/__init__.py
ebusdpy/ebusdpy.py
ebusdpy-0.0.16.dist-info/LICENSE
ebusdpy-0.0.16.dist-info/METADATA
ebusdpy-0.0.16.dist-info/WHEEL
ebusdpy-0.0.16.dist-info/top_level.txt
ebusdpy-0.0.16.dist-info/RECORD
